{
  "releases": [
    {
      "title": "collectZ v3.9.15",
      "version": "3.9.15",
      "date": null,
      "status": null,
      "summary": "",
      "details": []
    },
    {
      "title": "collectZ v3.9.14",
      "version": "3.9.14",
      "date": null,
      "status": null,
      "summary": "",
      "details": []
    },
    {
      "title": "collectZ v3.9.13",
      "version": "3.9.13",
      "date": null,
      "status": null,
      "summary": "",
      "details": []
    },
    {
      "title": "collectZ v3.9.12",
      "version": "3.9.12",
      "date": null,
      "status": null,
      "summary": "",
      "details": []
    },
    {
      "title": "collectZ v3.9.11",
      "version": "3.9.11",
      "date": null,
      "status": null,
      "summary": "",
      "details": []
    },
    {
      "title": "collectZ v3.9.10",
      "version": "3.9.10",
      "date": null,
      "status": null,
      "summary": "",
      "details": []
    },
    {
      "title": "collectZ v3.9.9",
      "version": "3.9.9",
      "date": null,
      "status": null,
      "summary": "",
      "details": []
    },
    {
      "title": "collectZ v3.9.8",
      "version": "3.9.8",
      "date": null,
      "status": null,
      "summary": "",
      "details": []
    },
    {
      "title": "collectZ v3.9.7",
      "version": "3.9.7",
      "date": null,
      "status": null,
      "summary": "",
      "details": []
    },
    {
      "title": "collectZ v3.9.6",
      "version": "3.9.6",
      "date": null,
      "status": null,
      "summary": "",
      "details": []
    }
  ]
}
